pvdb.py
pvdb-0.2.6.dist-info/DESCRIPTION.rst
pvdb-0.2.6.dist-info/METADATA
pvdb-0.2.6.dist-info/RECORD
pvdb-0.2.6.dist-info/WHEEL
pvdb-0.2.6.dist-info/entry_points.txt
pvdb-0.2.6.dist-info/metadata.json
pvdb-0.2.6.dist-info/top_level.txt
