Metadata-Version: 2.0
Name: pvdb
Version: 0.2.6
Summary: Python visual debugger inspired by Philip Guo's Python Tutor
Home-page: https://github.com/sdrave/pvdb
Author: Stephan Rave
Author-email: UNKNOWN
License: GPL-3.0+
Platform: UNKNOWN
Classifier: Development Status :: 3 - Alpha
Classifier: License :: OSI Approved :: GNU General Public License v3 or later (GPLv3+)
Classifier: Programming Language :: Python :: 3.4
Classifier: Programming Language :: Python :: 3.5
Classifier: Programming Language :: Python :: 3.6
Classifier: Topic :: Software Development :: Debuggers
Classifier: Intended Audience :: Education
Classifier: Intended Audience :: Developers
Requires-Dist: graphviz
Requires-Dist: pillow
